django_npm/__init__.py
django_npm/finders.py
django_npm/management/__init__.py
django_npm/management/commands/__init__.py
django_npm/management/commands/npm_install.py
django_npm_finder-1.2.0.dist-info/licenses/LICENSE
django_npm_finder-1.2.0.dist-info/WHEEL
django_npm_finder-1.2.0.dist-info/METADATA
django_npm_finder-1.2.0.dist-info/RECORD
