Metadata-Version: 2.4
Name: django-npm-finder
Version: 1.2.0
Summary: A django staticfiles finder that supporting npm/yarn/pnpm
Keywords: django,npm,finder,staticfiles
Author-email: David Nugent <davidn@uniquode.io>, Kevin McCarthy <e@kevinmccarthy.org>
Requires-Python: >=3.10,<4.0
Classifier: Development Status :: 3 - Alpha
Classifier: Intended Audience :: Developers
Classifier: Topic :: Software Development :: Build Tools
Classifier: License :: OSI Approved :: MIT License
Classifier: Programming Language :: Python :: 3.10
Classifier: Programming Language :: Python :: 3.11
Classifier: Programming Language :: Python :: 3.12
License-File: LICENSE
Requires-Dist: Django>=4.2
Project-URL: Documentation, https://github.com/deeprave/django-npm-finder
Project-URL: Homepage, https://github.com/deeprave/django-npm-finder
Project-URL: Repository, https://github.com/deeprave/django-npm-finder
